textualheatmap/__init__.py
textualheatmap/textual_heatmap.py
textualheatmap/textual_heatmap_test.py
textualheatmap/web_assets/textual_heatmap.css
textualheatmap/web_assets/textual_heatmap.js
textualheatmap-1.2.0.dist-info/LICENSE.txt
textualheatmap-1.2.0.dist-info/METADATA
textualheatmap-1.2.0.dist-info/WHEEL
textualheatmap-1.2.0.dist-info/top_level.txt
textualheatmap-1.2.0.dist-info/RECORD
