Metadata-Version: 2.1
Name: textualheatmap
Version: 1.2.0
Summary: Create interactive textual heat maps for Jupiter notebooks
Author-email: Andreas Madsen <amwebdk@gmail.com>
License: MIT
Keywords: saliency,heatmap,text,textual,jupyter,colab,interactive
Classifier: Development Status :: 5 - Production/Stable
Classifier: Intended Audience :: Developers
Classifier: Intended Audience :: Education
Classifier: Intended Audience :: Science/Research
Classifier: License :: OSI Approved :: MIT License
Classifier: Programming Language :: Python :: 3
Classifier: Programming Language :: Python :: 3.6
Classifier: Topic :: Software Development :: Libraries
Classifier: Topic :: Software Development :: Libraries :: Python Modules
Requires-Python: >=3.8
License-File: LICENSE.txt
Requires-Dist: ipython
Provides-Extra: testing
Requires-Dist: nose ; extra == 'testing'
Requires-Dist: jupyterlab ; extra == 'testing'
Requires-Dist: tensorflow ; extra == 'testing'
